{
  "unpublishedPage": {
    "name": "Influencer Analytics",
    "slug": "influencer-analytics",
    "layouts": [
      {
        "viewMode": false,
        "dsl": {
          "widgetName": "MainContainer",
          "backgroundColor": "none",
          "rightColumn": 1224,
          "snapColumns": 64,
          "detachFromLayout": true,
          "widgetId": "0",
          "topRow": 0,
          "bottomRow": 700,
          "containerStyle": "none",
          "snapRows": 83,
          "parentRowSpace": 1,
          "type": "CANVAS_WIDGET",
          "canExtend": true,
          "version": 87,
          "minHeight": 850,
          "parentColumnSpace": 1,
          "dynamicBindingPathList": [],
          "leftColumn": 0
        },
        "layoutOnLoadActions": [
          [
            {
              "id": "Influencer Analytics_get_all_brands",
              "name": "get_all_brands",
              "confirmBeforeExecute": false,
              "pluginType": "API",
              "jsonPathKeys": [],
              "timeoutInMillisecond": 10000
            }
          ],
          [
            {
              "id": "Influencer Analytics_followers",
              "name": "followers",
              "confirmBeforeExecute": false,
              "pluginType": "API",
              "jsonPathKeys": [
                "appsmith.store.user.username"
              ],
              "timeoutInMillisecond": 10000
            }
          ],
          [
            {
              "id": "Influencer Analytics_bio",
              "name": "bio",
              "confirmBeforeExecute": false,
              "pluginType": "API",
              "jsonPathKeys": [
                "appsmith.store.user.username"
              ],
              "timeoutInMillisecond": 10000
            },
            {
              "id": "Influencer Analytics_interactions",
              "name": "interactions",
              "confirmBeforeExecute": false,
              "pluginType": "API",
              "jsonPathKeys": [
                "appsmith.store.user.username"
              ],
              "timeoutInMillisecond": 10000
            }
          ]
        ],
        "layoutOnLoadActionErrors": [],
        "validOnPageLoadActions": true,
        "id": "Influencer Analytics",
        "deleted": false,
        "policies": [],
        "userPermissions": []
      }
    ],
    "userPermissions": [],
    "policies": [],
    "isHidden": false
  },
  "deleted": false,
  "gitSyncId": "656ff3c14b88fa48ff0634d7_657001bc4b88fa48ff06357c"
}